{"is_source_file": true, "format": "Python", "description": "This file contains Pydantic models for a task management backend API, including user, task, and authentication schemas.", "external_files": ["pydantic", "typing", "datetime"], "external_methods": ["BaseModel", "EmailStr", "Field", "Optional", "List", "datetime", "date", "timedelta"], "published": ["UserSignup", "UserLogin", "UserRead", "TokenResponse", "TaskCreate", "TaskUpdate", "TaskRead", "TaskListResponse", "MessageResponse"], "classes": [{"name": "UserSignup", "description": "Schema for a new user signup request."}, {"name": "UserLogin", "description": "Schema for user login requests."}, {"name": "UserRead", "description": "Response schema for user data."}, {"name": "TokenResponse", "description": "Response schema for login/token requests."}, {"name": "TaskBase", "description": "Base schema for a task (shared props)."}, {"name": "TaskCreate", "description": "Schema for creating a new task."}, {"name": "TaskUpdate", "description": "Schema for updating a task."}, {"name": "TaskRead", "description": "Schema for returning a task."}, {"name": "TaskListResponse", "description": "Response schema for a list of tasks."}, {"name": "MessageResponse", "description": "Generic response with a message."}], "methods": [], "calls": [], "search-terms": ["Pydantic", "API schema", "user models", "task models", "authentication"], "state": 2, "file_id": 5, "knowledge_revision": 11, "git_revision": "", "ctags": [{"_type": "tag", "name": "MessageResponse", "path": "/home/kavia/workspace/code-generation/task-organizer-pro-108370-536/task_management_backend/src/api/models.py", "pattern": "/^class MessageResponse(BaseModel):$/", "language": "Python", "kind": "class"}, {"_type": "tag", "name": "TaskBase", "path": "/home/kavia/workspace/code-generation/task-organizer-pro-108370-536/task_management_backend/src/api/models.py", "pattern": "/^class TaskBase(BaseModel):$/", "language": "Python", "kind": "class"}, {"_type": "tag", "name": "TaskCreate", "path": "/home/kavia/workspace/code-generation/task-organizer-pro-108370-536/task_management_backend/src/api/models.py", "pattern": "/^class TaskCreate(TaskBase):$/", "language": "Python", "kind": "class"}, {"_type": "tag", "name": "TaskListResponse", "path": "/home/kavia/workspace/code-generation/task-organizer-pro-108370-536/task_management_backend/src/api/models.py", "pattern": "/^class TaskListResponse(BaseModel):$/", "language": "Python", "kind": "class"}, {"_type": "tag", "name": "TaskRead", "path": "/home/kavia/workspace/code-generation/task-organizer-pro-108370-536/task_management_backend/src/api/models.py", "pattern": "/^class TaskRead(TaskBase):$/", "language": "Python", "kind": "class"}, {"_type": "tag", "name": "TaskUpdate", "path": "/home/kavia/workspace/code-generation/task-organizer-pro-108370-536/task_management_backend/src/api/models.py", "pattern": "/^class TaskUpdate(BaseModel):$/", "language": "Python", "kind": "class"}, {"_type": "tag", "name": "TokenResponse", "path": "/home/kavia/workspace/code-generation/task-organizer-pro-108370-536/task_management_backend/src/api/models.py", "pattern": "/^class TokenResponse(BaseModel):$/", "language": "Python", "kind": "class"}, {"_type": "tag", "name": "UserLogin", "path": "/home/kavia/workspace/code-generation/task-organizer-pro-108370-536/task_management_backend/src/api/models.py", "pattern": "/^class UserLogin(BaseModel):$/", "language": "Python", "kind": "class"}, {"_type": "tag", "name": "UserRead", "path": "/home/kavia/workspace/code-generation/task-organizer-pro-108370-536/task_management_backend/src/api/models.py", "pattern": "/^class UserRead(BaseModel):$/", "language": "Python", "kind": "class"}, {"_type": "tag", "name": "UserSignup", "path": "/home/kavia/workspace/code-generation/task-organizer-pro-108370-536/task_management_backend/src/api/models.py", "pattern": "/^class UserSignup(BaseModel):$/", "language": "Python", "kind": "class"}, {"_type": "tag", "name": "assignee_id", "path": "/home/kavia/workspace/code-generation/task-organizer-pro-108370-536/task_management_backend/src/api/models.py", "pattern": "/^    assignee_id: Optional[int] = Field(None, description=\"ID of assigned user (optional for crea/", "language": "Python", "typeref": "typename:Optional[int]", "kind": "variable", "scope": "TaskCreate", "scopeKind": "class"}, {"_type": "tag", "name": "assignee_id", "path": "/home/kavia/workspace/code-generation/task-organizer-pro-108370-536/task_management_backend/src/api/models.py", "pattern": "/^    assignee_id: Optional[int] = None$/", "language": "Python", "typeref": "typename:Optional[int]", "kind": "variable", "scope": "TaskRead", "scopeKind": "class"}, {"_type": "tag", "name": "assignee_id", "path": "/home/kavia/workspace/code-generation/task-organizer-pro-108370-536/task_management_backend/src/api/models.py", "pattern": "/^    assignee_id: Optional[int] = None$/", "language": "Python", "typeref": "typename:Optional[int]", "kind": "variable", "scope": "TaskUpdate", "scopeKind": "class"}, {"_type": "tag", "name": "description", "path": "/home/kavia/workspace/code-generation/task-organizer-pro-108370-536/task_management_backend/src/api/models.py", "pattern": "/^    description: Optional[str] = None$/", "language": "Python", "typeref": "typename:Optional[str]", "kind": "variable", "scope": "TaskBase", "scopeKind": "class"}, {"_type": "tag", "name": "description", "path": "/home/kavia/workspace/code-generation/task-organizer-pro-108370-536/task_management_backend/src/api/models.py", "pattern": "/^    description: Optional[str] = None$/", "language": "Python", "typeref": "typename:Optional[str]", "kind": "variable", "scope": "TaskUpdate", "scopeKind": "class"}, {"_type": "tag", "name": "due_date", "path": "/home/kavia/workspace/code-generation/task-organizer-pro-108370-536/task_management_backend/src/api/models.py", "pattern": "/^    due_date: Optional[date] = Field(None, description=\"Task due date (reminder placeholder)\")$/", "language": "Python", "typeref": "typename:Optional[date]", "kind": "variable", "scope": "TaskBase", "scopeKind": "class"}, {"_type": "tag", "name": "due_date", "path": "/home/kavia/workspace/code-generation/task-organizer-pro-108370-536/task_management_backend/src/api/models.py", "pattern": "/^    due_date: Optional[date] = None$/", "language": "Python", "typeref": "typename:Optional[date]", "kind": "variable", "scope": "TaskUpdate", "scopeKind": "class"}, {"_type": "tag", "name": "email", "path": "/home/kavia/workspace/code-generation/task-organizer-pro-108370-536/task_management_backend/src/api/models.py", "pattern": "/^    email: EmailStr = Field(..., description=\"User email address (unique)\")$/", "language": "Python", "typeref": "typename:EmailStr", "kind": "variable", "scope": "UserSignup", "scopeKind": "class"}, {"_type": "tag", "name": "email", "path": "/home/kavia/workspace/code-generation/task-organizer-pro-108370-536/task_management_backend/src/api/models.py", "pattern": "/^    email: EmailStr = Field(..., description=\"User email address\")$/", "language": "Python", "typeref": "typename:EmailStr", "kind": "variable", "scope": "UserLogin", "scopeKind": "class"}, {"_type": "tag", "name": "full_name", "path": "/home/kavia/workspace/code-generation/task-organizer-pro-108370-536/task_management_backend/src/api/models.py", "pattern": "/^    full_name: Optional[str] = Field(None, description=\"Full name of the user\")$/", "language": "Python", "typeref": "typename:Optional[str]", "kind": "variable", "scope": "UserSignup", "scopeKind": "class"}, {"_type": "tag", "name": "full_name", "path": "/home/kavia/workspace/code-generation/task-organizer-pro-108370-536/task_management_backend/src/api/models.py", "pattern": "/^    full_name: Optional[str] = None$/", "language": "Python", "typeref": "typename:Optional[str]", "kind": "variable", "scope": "UserRead", "scopeKind": "class"}, {"_type": "tag", "name": "password", "path": "/home/kavia/workspace/code-generation/task-organizer-pro-108370-536/task_management_backend/src/api/models.py", "pattern": "/^    password: str = Field(..., min_length=6, description=\"User password (hashed in actual implem/", "language": "Python", "typeref": "typename:str", "kind": "variable", "scope": "UserSignup", "scopeKind": "class"}, {"_type": "tag", "name": "password", "path": "/home/kavia/workspace/code-generation/task-organizer-pro-108370-536/task_management_backend/src/api/models.py", "pattern": "/^    password: str = Field(..., min_length=6, description=\"User password\")$/", "language": "Python", "typeref": "typename:str", "kind": "variable", "scope": "UserLogin", "scopeKind": "class"}, {"_type": "tag", "name": "status", "path": "/home/kavia/workspace/code-generation/task-organizer-pro-108370-536/task_management_backend/src/api/models.py", "pattern": "/^    status: Optional[str] = None$/", "language": "Python", "typeref": "typename:Optional[str]", "kind": "variable", "scope": "TaskUpdate", "scopeKind": "class"}, {"_type": "tag", "name": "status", "path": "/home/kavia/workspace/code-generation/task-organizer-pro-108370-536/task_management_backend/src/api/models.py", "pattern": "/^    status: str = Field(\"todo\", description=\"Current status (todo|in_progress|done)\")$/", "language": "Python", "typeref": "typename:str", "kind": "variable", "scope": "TaskBase", "scopeKind": "class"}, {"_type": "tag", "name": "title", "path": "/home/kavia/workspace/code-generation/task-organizer-pro-108370-536/task_management_backend/src/api/models.py", "pattern": "/^    title: Optional[str] = None$/", "language": "Python", "typeref": "typename:Optional[str]", "kind": "variable", "scope": "TaskUpdate", "scopeKind": "class"}, {"_type": "tag", "name": "token_type", "path": "/home/kavia/workspace/code-generation/task-organizer-pro-108370-536/task_management_backend/src/api/models.py", "pattern": "/^    token_type: str = \"bearer\"$/", "language": "Python", "typeref": "typename:str", "kind": "variable", "scope": "TokenResponse", "scopeKind": "class"}], "hash": "c126c64737fd5ba09b56cedbfea375a8", "format-version": 4, "code-base-name": "task_management_backend", "filename": "task_management_backend/src/api/models.py", "fields": [{"name": "Optional[int] assignee_id", "scope": "TaskCreate", "scopeKind": "class", "description": "unavailable"}, {"name": "Optional[str] description", "scope": "TaskBase", "scopeKind": "class", "description": "unavailable"}, {"name": "Optional[date] due_date", "scope": "TaskBase", "scopeKind": "class", "description": "unavailable"}, {"name": "EmailStr email", "scope": "UserSignup", "scopeKind": "class", "description": "unavailable"}, {"name": "Optional[str] full_name", "scope": "UserSignup", "scopeKind": "class", "description": "unavailable"}, {"name": "str password", "scope": "UserSignup", "scopeKind": "class", "description": "unavailable"}, {"name": "Optional[str] status", "scope": "TaskUpdate", "scopeKind": "class", "description": "unavailable"}, {"name": "str status", "scope": "TaskBase", "scopeKind": "class", "description": "unavailable"}, {"name": "Optional[str] title", "scope": "TaskUpdate", "scopeKind": "class", "description": "unavailable"}, {"name": "str token_type", "scope": "TokenResponse", "scopeKind": "class", "description": "unavailable"}], "revision_history": [{"11": ""}]}